Metadata-Version: 1.0
Name: email-login
Version: 0.0.0
Summary: Please email me if you would like this project transferred
Home-page: UNKNOWN
Author: Perzan
Author-email: PerzanDevelopment@gmail.com
License: UNKNOWN
Platform: UNKNOWN
